{
    "annotations": {
        "list": [
            {
                "builtIn": 1,
                "datasource": "-- Grafana --",
                "enable": true,
                "hide": true,
                "iconColor": "rgba(0, 211, 255, 1)",
                "name": "Annotations & Alerts",
                "type": "dashboard"
            }
        ]
    },
    "editable": true,
    "gnetId": null,
    "graphTooltip": 0,
    "links": [],
    "panels": [
        {
            "collapsed": false,
            "datasource": null,
            "gridPos": {
                "h": 1,
                "w": 24,
                "x": 0,
                "y": 0
            },
            "id": 31,
            "panels": [],
            "title": "Node request",
            "type": "row"
        },
        {
            "datasource": null,
            "fieldConfig": {
                "defaults": {
                    "custom": {},
                    "mappings": [],
                    "thresholds": {
                        "mode": "absolute",
                        "steps": [
                            {
                                "color": "green",
                                "value": null
                            },
                            {
                                "color": "red",
                                "value": 80
                            }
                        ]
                    }
                },
                "overrides": []
            },
            "gridPos": {
                "h": 9,
                "w": 12,
                "x": 0,
                "y": 1
            },
            "id": 23,
            "options": {
                "displayMode": "gradient",
                "orientation": "auto",
                "reduceOptions": {
                    "calcs": [
                        "mean"
                    ],
                    "fields": "",
                    "values": false
                },
                "showUnfilled": true
            },
            "pluginVersion": "7.1.5",
            "targets": [
                {
                    "expr": "sum by (le) (rate(http_request_duration_seconds_bucket[$__interval]))",
                    "format": "time_series",
                    "instant": false,
                    "interval": "",
                    "intervalFactor": 10,
                    "legendFormat": "{{le}}",
                    "refId": "A"
                }
            ],
            "timeFrom": null,
            "timeShift": null,
            "title": "Node Request Duration Summary",
            "type": "bargauge"
        },
        {
            "datasource": null,
            "fieldConfig": {
                "defaults": {
                    "custom": {},
                    "decimals": 2,
                    "mappings": [],
                    "thresholds": {
                        "mode": "absolute",
                        "steps": [
                            {
                                "color": "red",
                                "value": null
                            },
                            {
                                "color": "#EAB839",
                                "value": 99
                            },
                            {
                                "color": "green",
                                "value": 99.9
                            }
                        ]
                    },
                    "unit": "%"
                },
                "overrides": []
            },
            "gridPos": {
                "h": 9,
                "w": 12,
                "x": 12,
                "y": 1
            },
            "id": 26,
            "interval": "1m",
            "options": {
                "colorMode": "value",
                "graphMode": "area",
                "justifyMode": "auto",
                "orientation": "auto",
                "reduceOptions": {
                    "calcs": [
                        "mean"
                    ],
                    "fields": "",
                    "values": false
                },
                "textMode": "auto"
            },
            "pluginVersion": "7.1.5",
            "targets": [
                {
                    "expr": "(sum by (app) (increase(http_request_duration_seconds_bucket{le=\"0.3\"}[1d])) / sum by (app) (increase(http_request_duration_seconds_count[1d]))) * 100",
                    "interval": "",
                    "legendFormat": "",
                    "refId": "A"
                }
            ],
            "timeFrom": null,
            "timeShift": null,
            "title": "Percentage of requests shorter than 0.3 seconds",
            "type": "stat"
        },
        {
            "aliasColors": {},
            "bars": false,
            "dashLength": 10,
            "dashes": false,
            "datasource": null,
            "fieldConfig": {
                "defaults": {
                    "custom": {}
                },
                "overrides": []
            },
            "fill": 1,
            "fillGradient": 0,
            "gridPos": {
                "h": 8,
                "w": 8,
                "x": 0,
                "y": 10
            },
            "hiddenSeries": false,
            "id": 12,
            "legend": {
                "avg": false,
                "current": false,
                "max": false,
                "min": false,
                "show": true,
                "total": false,
                "values": false
            },
            "lines": true,
            "linewidth": 1,
            "nullPointMode": "null",
            "options": {
                "alertThreshold": true
            },
            "percentage": false,
            "pluginVersion": "7.1.5",
            "pointradius": 2,
            "points": false,
            "renderer": "flot",
            "seriesOverrides": [],
            "spaceLength": 10,
            "stack": false,
            "steppedLine": false,
            "targets": [
                {
                    "expr": "sum(rate(http_request_duration_seconds_count[2m]))",
                    "interval": "",
                    "legendFormat": "{{app}}",
                    "refId": "A"
                }
            ],
            "thresholds": [],
            "timeFrom": null,
            "timeRegions": [],
            "timeShift": null,
            "title": "Node - Requests Per Second",
            "tooltip": {
                "shared": true,
                "sort": 0,
                "value_type": "individual"
            },
            "type": "graph",
            "xaxis": {
                "buckets": null,
                "mode": "time",
                "name": null,
                "show": true,
                "values": []
            },
            "yaxes": [
                {
                    "format": "reqps",
                    "label": "",
                    "logBase": 1,
                    "max": null,
                    "min": null,
                    "show": true
                },
                {
                    "format": "short",
                    "label": null,
                    "logBase": 1,
                    "max": null,
                    "min": null,
                    "show": true
                }
            ],
            "yaxis": {
                "align": false,
                "alignLevel": null
            }
        },
        {
            "cards": {
                "cardPadding": null,
                "cardRound": null
            },
            "color": {
                "cardColor": "#FADE2A",
                "colorScale": "sqrt",
                "colorScheme": "interpolateOranges",
                "exponent": 0.3,
                "max": null,
                "mode": "opacity"
            },
            "dataFormat": "tsbuckets",
            "datasource": null,
            "fieldConfig": {
                "defaults": {
                    "custom": {}
                },
                "overrides": []
            },
            "gridPos": {
                "h": 8,
                "w": 8,
                "x": 8,
                "y": 10
            },
            "heatmap": {},
            "hideZeroBuckets": true,
            "highlightCards": true,
            "id": 22,
            "legend": {
                "show": true
            },
            "pluginVersion": "7.3.5",
            "reverseYBuckets": false,
            "targets": [
                {
                    "expr": "label_replace(sum by (le) (increase(http_request_duration_seconds_bucket[1d])), \"le\", \"Inf\", \"le\", \"\\\\+Inf\")",
                    "format": "heatmap",
                    "instant": false,
                    "interval": "",
                    "intervalFactor": 10,
                    "legendFormat": "{{le}} ",
                    "refId": "A"
                }
            ],
            "timeFrom": null,
            "timeShift": null,
            "title": "Node Reqeust Duration Heatmap",
            "tooltip": {
                "show": true,
                "showHistogram": false
            },
            "transformations": [],
            "type": "heatmap",
            "xAxis": {
                "show": true
            },
            "xBucketNumber": null,
            "xBucketSize": null,
            "yAxis": {
                "decimals": 2,
                "format": "s",
                "logBase": 1,
                "max": null,
                "min": null,
                "show": true,
                "splitFactor": null
            },
            "yBucketBound": "middle",
            "yBucketNumber": null,
            "yBucketSize": null
        },
        {
            "aliasColors": {},
            "bars": false,
            "dashLength": 10,
            "dashes": false,
            "datasource": null,
            "fieldConfig": {
                "defaults": {
                    "custom": {}
                },
                "overrides": []
            },
            "fill": 1,
            "fillGradient": 0,
            "gridPos": {
                "h": 8,
                "w": 8,
                "x": 16,
                "y": 10
            },
            "hiddenSeries": false,
            "id": 27,
            "legend": {
                "avg": false,
                "current": false,
                "max": false,
                "min": false,
                "show": true,
                "total": false,
                "values": false
            },
            "lines": true,
            "linewidth": 1,
            "nullPointMode": "null",
            "options": {
                "alertThreshold": true
            },
            "percentage": false,
            "pluginVersion": "7.1.5",
            "pointradius": 2,
            "points": false,
            "renderer": "flot",
            "seriesOverrides": [],
            "spaceLength": 10,
            "stack": false,
            "steppedLine": false,
            "targets": [
                {
                    "expr": "(sum (rate(http_request_duration_seconds_bucket{le=\"0.3\"}[2m])) / sum(rate(http_request_duration_seconds_count[2m]))) * 100",
                    "interval": "",
                    "legendFormat": "",
                    "refId": "A"
                }
            ],
            "thresholds": [
                {
                    "colorMode": "critical",
                    "fill": true,
                    "line": true,
                    "op": "lt",
                    "value": 99,
                    "yaxis": "left"
                }
            ],
            "timeFrom": null,
            "timeRegions": [],
            "timeShift": null,
            "title": "Percentage of requests shorter than 0.3 seconds",
            "tooltip": {
                "shared": true,
                "sort": 0,
                "value_type": "individual"
            },
            "type": "graph",
            "xaxis": {
                "buckets": null,
                "mode": "time",
                "name": null,
                "show": true,
                "values": []
            },
            "yaxes": [
                {
                    "format": "%",
                    "label": null,
                    "logBase": 1,
                    "max": "100",
                    "min": null,
                    "show": true
                },
                {
                    "format": "short",
                    "label": null,
                    "logBase": 1,
                    "max": null,
                    "min": null,
                    "show": true
                }
            ],
            "yaxis": {
                "align": false,
                "alignLevel": null
            }
        },
        {
            "aliasColors": {},
            "bars": false,
            "dashLength": 10,
            "dashes": false,
            "datasource": null,
            "fieldConfig": {
                "defaults": {
                    "custom": {}
                },
                "overrides": []
            },
            "fill": 1,
            "fillGradient": 0,
            "gridPos": {
                "h": 8,
                "w": 8,
                "x": 0,
                "y": 18
            },
            "hiddenSeries": false,
            "id": 8,
            "legend": {
                "avg": false,
                "current": false,
                "max": false,
                "min": false,
                "show": true,
                "total": false,
                "values": false
            },
            "lines": true,
            "linewidth": 1,
            "nullPointMode": "null",
            "options": {
                "alertThreshold": true
            },
            "percentage": false,
            "pluginVersion": "7.1.5",
            "pointradius": 2,
            "points": false,
            "renderer": "flot",
            "seriesOverrides": [],
            "spaceLength": 10,
            "stack": false,
            "steppedLine": false,
            "targets": [
                {
                    "expr": "sum by (le) (rate(http_request_duration_seconds_bucket[3m]))\n",
                    "interval": "",
                    "legendFormat": "Requests > {{le}}s per second",
                    "refId": "A"
                }
            ],
            "thresholds": [],
            "timeFrom": null,
            "timeRegions": [],
            "timeShift": null,
            "title": "Node Request Duration (Stacked All Buckets)",
            "tooltip": {
                "shared": true,
                "sort": 0,
                "value_type": "individual"
            },
            "type": "graph",
            "xaxis": {
                "buckets": null,
                "mode": "time",
                "name": null,
                "show": true,
                "values": []
            },
            "yaxes": [
                {
                    "format": "short",
                    "label": null,
                    "logBase": 1,
                    "max": null,
                    "min": null,
                    "show": true
                },
                {
                    "format": "short",
                    "label": null,
                    "logBase": 1,
                    "max": null,
                    "min": null,
                    "show": true
                }
            ],
            "yaxis": {
                "align": false,
                "alignLevel": null
            }
        },
        {
            "aliasColors": {},
            "bars": false,
            "dashLength": 10,
            "dashes": false,
            "datasource": null,
            "fieldConfig": {
                "defaults": {
                    "custom": {}
                },
                "overrides": []
            },
            "fill": 1,
            "fillGradient": 0,
            "gridPos": {
                "h": 8,
                "w": 8,
                "x": 8,
                "y": 18
            },
            "hiddenSeries": false,
            "id": 20,
            "legend": {
                "avg": false,
                "current": false,
                "max": false,
                "min": false,
                "show": true,
                "total": false,
                "values": false
            },
            "lines": true,
            "linewidth": 1,
            "nullPointMode": "null",
            "options": {
                "alertThreshold": true
            },
            "percentage": false,
            "pluginVersion": "7.1.5",
            "pointradius": 2,
            "points": false,
            "renderer": "flot",
            "seriesOverrides": [],
            "spaceLength": 10,
            "stack": false,
            "steppedLine": false,
            "targets": [
                {
                    "expr": "sum (rate(http_request_duration_seconds_bucket{le=\"0.003\"}[3m]))",
                    "hide": true,
                    "interval": "",
                    "legendFormat": "t  <  0.003",
                    "refId": "A"
                },
                {
                    "expr": "sum (rate(http_request_duration_seconds_bucket{le=\"0.03\"}[3m])) - sum (rate(http_request_duration_seconds_bucket{le=\"0.003\"}[3m]))",
                    "interval": "",
                    "legendFormat": "0.003  <  t  <  0.03",
                    "refId": "B"
                },
                {
                    "expr": "sum (rate(http_request_duration_seconds_bucket{le=\"0.1\"}[3m])) - sum (rate(http_request_duration_seconds_bucket{le=\"0.03\"}[3m]))",
                    "interval": "",
                    "legendFormat": "0.03  <  t  <  0.1",
                    "refId": "C"
                },
                {
                    "expr": "sum (rate(http_request_duration_seconds_bucket{le=\"0.3\"}[3m])) - sum (rate(http_request_duration_seconds_bucket{le=\"0.1\"}[3m]))",
                    "interval": "",
                    "legendFormat": "0.1  <  t  < 0.3",
                    "refId": "D"
                },
                {
                    "expr": "sum (rate(http_request_duration_seconds_bucket{le=\"1.5\"}[3m])) - sum (rate(http_request_duration_seconds_bucket{le=\"0.3\"}[3m]))",
                    "interval": "",
                    "legendFormat": "0.3  <  t  <  1.5",
                    "refId": "E"
                },
                {
                    "expr": "sum (rate(http_request_duration_seconds_bucket{le=\"10\"}[3m])) - sum (rate(http_request_duration_seconds_bucket{le=\"1.5\"}[3m]))",
                    "interval": "",
                    "legendFormat": "1.5  <  t  <  10",
                    "refId": "F"
                },
                {
                    "expr": "sum (rate(http_request_duration_seconds_bucket{le=\"+Inf\"}[3m])) - sum (rate(http_request_duration_seconds_bucket{le=\"10\"}[3m]))",
                    "interval": "",
                    "legendFormat": "10  <  t",
                    "refId": "G"
                }
            ],
            "thresholds": [],
            "timeFrom": null,
            "timeRegions": [],
            "timeShift": null,
            "title": "Node Request Duration (Unstacked Buckets)",
            "tooltip": {
                "shared": true,
                "sort": 0,
                "value_type": "individual"
            },
            "type": "graph",
            "xaxis": {
                "buckets": null,
                "mode": "time",
                "name": null,
                "show": true,
                "values": []
            },
            "yaxes": [
                {
                    "format": "short",
                    "label": null,
                    "logBase": 1,
                    "max": null,
                    "min": null,
                    "show": true
                },
                {
                    "format": "short",
                    "label": null,
                    "logBase": 1,
                    "max": null,
                    "min": null,
                    "show": true
                }
            ],
            "yaxis": {
                "align": false,
                "alignLevel": null
            }
        },
        {
            "aliasColors": {},
            "bars": false,
            "dashLength": 10,
            "dashes": false,
            "datasource": null,
            "fieldConfig": {
                "defaults": {
                    "custom": {}
                },
                "overrides": []
            },
            "fill": 1,
            "fillGradient": 0,
            "gridPos": {
                "h": 8,
                "w": 8,
                "x": 16,
                "y": 18
            },
            "hiddenSeries": false,
            "id": 29,
            "legend": {
                "avg": false,
                "current": false,
                "max": false,
                "min": false,
                "show": true,
                "total": false,
                "values": false
            },
            "lines": true,
            "linewidth": 1,
            "nullPointMode": "null",
            "options": {
                "alertThreshold": true
            },
            "percentage": false,
            "pluginVersion": "7.1.5",
            "pointradius": 2,
            "points": false,
            "renderer": "flot",
            "seriesOverrides": [],
            "spaceLength": 10,
            "stack": false,
            "steppedLine": false,
            "targets": [
                {
                    "expr": "sum by (le) (rate(http_request_duration_seconds_count[3m]) - ignoring (le) group_right rate(http_request_duration_seconds_bucket{le!=\"+Inf\"}[3m]))",
                    "interval": "",
                    "legendFormat": "Requests > {{le}}s per second",
                    "refId": "A"
                }
            ],
            "thresholds": [],
            "timeFrom": null,
            "timeRegions": [],
            "timeShift": null,
            "title": "Node Request Duration (Stacked Buckets)",
            "tooltip": {
                "shared": true,
                "sort": 0,
                "value_type": "individual"
            },
            "type": "graph",
            "xaxis": {
                "buckets": null,
                "mode": "time",
                "name": null,
                "show": true,
                "values": []
            },
            "yaxes": [
                {
                    "format": "short",
                    "label": null,
                    "logBase": 1,
                    "max": null,
                    "min": null,
                    "show": true
                },
                {
                    "format": "short",
                    "label": null,
                    "logBase": 1,
                    "max": null,
                    "min": null,
                    "show": true
                }
            ],
            "yaxis": {
                "align": false,
                "alignLevel": null
            }
        }
    ],
    "refresh": false,
    "schemaVersion": 26,
    "style": "dark",
    "tags": [],
    "templating": {
        "list": []
    },
    "time": {
        "from": "now-1h",
        "to": "now"
    },
    "timepicker": {
        "refresh_intervals": [
            "5s",
            "10s",
            "30s",
            "1m",
            "5m",
            "15m",
            "30m",
            "1h",
            "2h",
            "1d"
        ]
    },
    "timezone": "",
    "title": "NodeJS Request Flow Dashboard",
    "uid": "2Er5E1R7k",
    "version": 2
}
